one_line_llm_tuner/__init__.py
one_line_llm_tuner/builder/__init__.py
one_line_llm_tuner/builder/text_file_builder.py
one_line_llm_tuner/dataset/__init__.py
one_line_llm_tuner/dataset/dataset_loader.py
one_line_llm_tuner/reader/__init__.py
one_line_llm_tuner/reader/file_reader.py
one_line_llm_tuner/tuner/__init__.py
one_line_llm_tuner/tuner/llm_tuner.py
one_line_llm_tuner-0.0.15.dist-info/METADATA
one_line_llm_tuner-0.0.15.dist-info/WHEEL
one_line_llm_tuner-0.0.15.dist-info/top_level.txt
one_line_llm_tuner-0.0.15.dist-info/RECORD
