Metadata-Version: 2.1
Name: one-line-llm-tuner
Version: 0.0.15
Summary: A Large Language Model Fine-tuning package. The package uses a single line to fine-tune an LLM by taking care of all the boilerplate in the backend.
Home-page: https://github.com/metriccoders/one-line-llm-tuner
Author: Suhas Bhairav
Author-email: info@metriccoders.com
Project-URL: Bug Tracker, https://github.com/metriccoders/one-line-llm-tuner/issues
Classifier: Programming Language :: Python :: 3.10
Classifier: License :: OSI Approved :: Apache Software License
Classifier: Operating System :: OS Independent
Requires-Python: >=3.10
Requires-Dist: scikit-learn>=0.24.0
Requires-Dist: transformers>=4.0.0
